pypidstat/__init__.py
pypidstat/pidstat.py
pypidstat/utils.py
pypidstat/base/__init__.py
pypidstat/base/fields.py
pypidstat/base/proc_sys.py
pypidstat/base/types.py
pypidstat/core/__init__.py
pypidstat/core/process_stat.py
pypidstat/net/__init__.py
pypidstat/net/dev.py
pypidstat/net/net.py
pypidstat/net/net_cap.py
pypidstat-0.1.dist-info/LICENSE
pypidstat-0.1.dist-info/METADATA
pypidstat-0.1.dist-info/WHEEL
pypidstat-0.1.dist-info/entry_points.txt
pypidstat-0.1.dist-info/top_level.txt
pypidstat-0.1.dist-info/RECORD
