Metadata-Version: 2.1
Name: pypidstat
Version: 0.1
Summary: python to implement pidstat and nethogs
Home-page: https://gitee.com/thirsd/pypidstat
Author: thirsd
Author-email: thirsd@sina.com
License: UNKNOWN
Platform: UNKNOWN
Classifier: Programming Language :: Python :: 3
Classifier: License :: OSI Approved :: MIT License
Classifier: Operating System :: OS Independent
License-File: LICENSE
Requires-Dist: dpkt (>=1.9.8)
Requires-Dist: libpcap (>=1.11.0b2)
Requires-Dist: pypcap (>=1.3.0)
